MANIFEST.in
README.md
pyproject.toml
setup.py
agora/__init__.py
agora/rtc/__init__.py
agora/rtc/agora_base.py
agora/rtc/agora_parameter.py
agora/rtc/agora_service.py
agora/rtc/audio_encoded_frame_sender.py
agora/rtc/audio_frame_observer.py
agora/rtc/audio_pcm_data_sender.py
agora/rtc/audio_sessionctrl.py
agora/rtc/audio_vad_manager.py
agora/rtc/external_audio_processor.py
agora/rtc/local_audio_track.py
agora/rtc/local_user.py
agora/rtc/local_user_observer.py
agora/rtc/local_video_track.py
agora/rtc/media_node_factory.py
agora/rtc/remote_audio_track.py
agora/rtc/remote_video_track.py
agora/rtc/rtc_connection.py
agora/rtc/rtc_connection_observer.py
agora/rtc/video_encoded_frame_observer.py
agora/rtc/video_encoded_image_sender.py
agora/rtc/video_frame_observer.py
agora/rtc/video_frame_sender.py
agora/rtc/voice_detection.py
agora/rtc/_ctypes_handle/_audio_frame_observer.py
agora/rtc/_ctypes_handle/_ctypes_data.py
agora/rtc/_ctypes_handle/_local_user_observer.py
agora/rtc/_ctypes_handle/_rtc_connection_observer.py
agora/rtc/_ctypes_handle/_video_encoded_frame_observer.py
agora/rtc/_ctypes_handle/_video_frame_observer.py
agora/rtc/_utils/globals.py
agora/rtc/utils/audio_consumer.py
agora/rtc/utils/vad_dump.py
agora/rtm/__init__.py
agora/rtm/rtm_base.py
agora/rtm/rtm_client.py
agora/rtm/rtm_event_handler.py
agora/rtm/_ctypes_handle/_ctypes_data.py
agora_python_server_sdk.egg-info/PKG-INFO
agora_python_server_sdk.egg-info/SOURCES.txt
agora_python_server_sdk.egg-info/dependency_links.txt
agora_python_server_sdk.egg-info/top_level.txt