Metadata-Version: 2.1
Name: agora_python_server_sdk
Version: 2.4.2
Summary: A Python SDK for Agora Server
Home-page: https://github.com/AgoraIO-Extensions/Agora-Python-Server-SDK
Classifier: Intended Audience :: Developers
Classifier: License :: OSI Approved :: MIT License
Classifier: Topic :: Multimedia :: Sound/Audio
Classifier: Topic :: Multimedia :: Video
Classifier: Topic :: Scientific/Engineering :: Artificial Intelligence
Classifier: Programming Language :: Python :: 3.10
Classifier: Programming Language :: Python :: 3 :: Only
Requires-Python: >=3.10
